simple_image2ascii/__init__.py
simple_image2ascii/ascii_engine.py
simple_image2ascii-0.0.2.dist-info/licenses/LICENSE
simple_image2ascii-0.0.2.dist-info/METADATA
simple_image2ascii-0.0.2.dist-info/WHEEL
simple_image2ascii-0.0.2.dist-info/top_level.txt
simple_image2ascii-0.0.2.dist-info/RECORD
