Metadata-Version: 2.4
Name: simple-image2ascii
Version: 0.0.2
Summary: A Python library for converting images and videos into ASCII art.
Home-page: https://github.com/AlekseyScorpi/simple-image2ascii
Author: Aleksey Timoshin
Author-email: timoshin_aleksey02@mail.ru
Classifier: Programming Language :: Python :: 3
Classifier: License :: OSI Approved :: MIT License
Classifier: Operating System :: OS Independent
Requires-Python: >=3.8
License-File: LICENSE
Requires-Dist: numpy
Requires-Dist: opencv-python
Dynamic: author
Dynamic: author-email
Dynamic: classifier
Dynamic: description
Dynamic: description-content-type
Dynamic: home-page
Dynamic: license-file
Dynamic: requires-dist
Dynamic: requires-python
Dynamic: summary
